geco_explainer/__init__.py
geco_explainer/geco_explainer.py
geco_explainer-0.2.3.dist-info/licenses/LICENSE.txt
geco_explainer-0.2.3.dist-info/METADATA
geco_explainer-0.2.3.dist-info/WHEEL
geco_explainer-0.2.3.dist-info/top_level.txt
geco_explainer-0.2.3.dist-info/RECORD
